bishop_bridge/__init__.py
bishop_bridge/bridge.py
bishop_bridge-0.0.5.dist-info/LICENSE
bishop_bridge-0.0.5.dist-info/METADATA
bishop_bridge-0.0.5.dist-info/WHEEL
bishop_bridge-0.0.5.dist-info/top_level.txt
bishop_bridge-0.0.5.dist-info/RECORD
