Metadata-Version: 2.1
Name: bishop-bridge
Version: 0.0.5
Summary: A package for creating a Bishop bridge
Author-email: Noah Hunn <nhunn@calvaryrobotics.com>
Project-URL: Homepage, https://github.com/CalvaryDesign/bishop-bridge
Classifier: Programming Language :: Python :: 3
Classifier: License :: OSI Approved :: MIT License
Classifier: Operating System :: OS Independent
Requires-Python: >=3.10
License-File: LICENSE
Requires-Dist: python-socketio
Requires-Dist: msgpack
